[
    {
        "position": [
            45,
            2
        ],
        "color": [
            153,
            182,
            255
        ]
    },
    {
        "position": [
            45,
            3
        ],
        "color": [
            153,
            182,
            255
        ]
    },
    {
        "position": [
            46,
            3
        ],
        "color": [
            153,
            182,
            255
        ]
    },
    {
        "position": [
            46,
            1
        ],
        "color": [
            153,
            182,
            255
        ]
    }
]